README.rst
setup.py
commondata.be.egg-info/PKG-INFO
commondata.be.egg-info/SOURCES.txt
commondata.be.egg-info/dependency_links.txt
commondata.be.egg-info/namespace_packages.txt
commondata.be.egg-info/requires.txt
commondata.be.egg-info/top_level.txt
commondata/be/__init__.py
commondata/be/antwerpen.py
commondata/be/brabantwallon.py
commondata/be/brussels.py
commondata/be/hainaut.py
commondata/be/liege.py
commondata/be/limburg.py
commondata/be/luxembourg.py
commondata/be/namur.py
commondata/be/oostvlaanderen.py
commondata/be/places.py
commondata/be/vlaamsbrabant.py
commondata/be/westvlaanderen.py