Metadata-Version: 1.1
Name: commondata.be
Version: 0.0.1
Summary: Common data about Belgium
Home-page: http://commondata.lino-framework.org
Author: Luc Saffre
Author-email: luc.saffre@gmail.com
License: GPL
Platform: UNKNOWN
Classifier: Programming Language :: Python
Classifier: Programming Language :: Python :: 2.6
Classifier: Programming Language :: Python :: 2.7
Classifier: Development Status :: 4 - Beta
Classifier: Intended Audience :: Developers
Classifier: License :: OSI Approved :: GNU General Public License (GPL)
Classifier: Natural Language :: English
Classifier: Operating System :: OS Independent
